yts_dl/__init__.py
yts_dl/main.py
yts_dl-0.0.2.dist-info/LICENSE
yts_dl-0.0.2.dist-info/METADATA
yts_dl-0.0.2.dist-info/WHEEL
yts_dl-0.0.2.dist-info/entry_points.txt
yts_dl-0.0.2.dist-info/top_level.txt
yts_dl-0.0.2.dist-info/RECORD
