Metadata-Version: 2.1
Name: yts-dl
Version: 0.0.2
Summary: Download from YouTube & Spotify
License: MIT License
License-File: LICENSE
Requires-Dist: colorlog
Requires-Dist: yt-dlp
Requires-Dist: spotdl
